mentium/__init__.py
mentium/logger/__init__.py
mentium/logger/async_logger.py
mentium/wrapper/__init__.py
mentium/wrapper/wrapper.py
mentium-0.1.2.dist-info/METADATA
mentium-0.1.2.dist-info/WHEEL
mentium-0.1.2.dist-info/RECORD
