Metadata-Version: 2.1
Name: mentium
Version: 0.1.2
Summary: 
Author: Matthieu B.
Author-email: matthieu@mentium.io
Requires-Python: >=3.9,<4.0
Classifier: Programming Language :: Python :: 3
Classifier: Programming Language :: Python :: 3.9
Classifier: Programming Language :: Python :: 3.10
Classifier: Programming Language :: Python :: 3.11
Requires-Dist: openai (>=0.27.9,<0.28.0)
Requires-Dist: requests (>=2.31.0,<3.0.0)
